trick/__init__.py
trick/compose.py
trick/curry.py
trick/identity.py
trick-0.1.0.dist-info/WHEEL
trick-0.1.0.dist-info/METADATA
trick-0.1.0.dist-info/LICENSE
trick-0.1.0.dist-info/RECORD
