Metadata-Version: 2.1
Name: trick
Version: 0.1.0
Summary: A collection of some helper functions
License: MIT
Author-email: Elliot <hack00mind@gmail.com>
Requires-Python: >=3.9
Classifier: License :: OSI Approved :: MIT License
Classifier: Programming Language :: Python :: 3
Classifier: Programming Language :: Python :: 3.9
Project-URL: homepage, https://github.com/Eliot00/python-trick
